gh_py/__init__.py
gh_py/cli.py
gh_py/internal/__init__.py
gh_py/internal/exe_runner.py
gh_py/internal/gh.py
gh_py/internal/git.py
gh_py/repository.py
gh_py/scaffolding/.gitignore
gh_py/scaffolding/__init__.py
gh_py/scaffolding/extension.py
gh_py/scaffolding/pyproject.toml
gh_py/scaffolding/scaffolding
gh_py-1.2.0.dist-info/entry_points.txt
gh_py-1.2.0.dist-info/LICENSE
gh_py-1.2.0.dist-info/WHEEL
gh_py-1.2.0.dist-info/METADATA
gh_py-1.2.0.dist-info/RECORD
